PKG-INFO
README.rst
setup.cfg
setup.py
BATS/AllocFinder.c
BATS/AllocFinder.pyx
BATS/BATS.py
BATS/BATS_MAMS.py
BATS/BATS_PosteriorProbability.py
BATS/BATS_eventfilter.py
BATS/BATS_messagebox.py
BATS/BATS_validator.py
BATS/CalPosteriorProbability.c
BATS/CriticalValueCal.c
BATS/CriticalValueCal.pxd
BATS/CriticalValueCal.pyx
BATS/FixedTrial.c
BATS/FixedTrial.pyx
BATS/FixedTrialData.c
BATS/FixedTrialData.pyx
BATS/GammaGenerate.c
BATS/GammaGenerate.pyx
BATS/InterimAnalysis.c
BATS/InterimAnalysis.pyx
BATS/PredictiveProbability.c
BATS/PredictiveProbability.pyx
BATS/__init__.py
BATS.egg-info/PKG-INFO
BATS.egg-info/SOURCES.txt
BATS.egg-info/dependency_links.txt
BATS.egg-info/not-zip-safe
BATS.egg-info/requires.txt
BATS.egg-info/top_level.txt
BATS/../README.rst
BATS/documentation/Documentation.pdf
BATS/qrc/__init__.py
BATS/qrc/resources_qr.py
BATS/resources/Icon.ico
BATS/resources/bcts.png
BATS/resources/close.png
BATS/resources/design.png
BATS/resources/design_selected.png
BATS/resources/doc.png
BATS/resources/dropdown_arrow.png
BATS/resources/dropdown_arrow_disabled.png
BATS/resources/error.png
BATS/resources/error_out.png
BATS/resources/input.png
BATS/resources/input_out.png
BATS/resources/maximize.png
BATS/resources/minimize.png
BATS/resources/other.png
BATS/resources/other_selected.png
BATS/resources/plot.png
BATS/resources/quit.png
BATS/resources/restore.png
BATS/resources/restore_btn.png
BATS/resources/result_log.png
BATS/resources/result_plot.png
BATS/resources/result_setting.png
BATS/resources/result_table.png
BATS/resources/runmenu.gif
BATS/resources/success.png
BATS/resources/success_out.png
BATS/resources/tab_info.png
BATS/resources/tab_info_disabled.png
BATS/resources/tab_info_disabled_out.png
BATS/resources/tab_log.png
BATS/resources/tab_log_disabled.png
BATS/resources/tab_log_disabled_out.png
BATS/resources/table.png
BATS/resources/table_selected.png
BATS/resources/toggle_off.png
BATS/resources/toggle_off_out.png
BATS/resources/toggle_on.png
BATS/resources/toggle_on_out.png
BATS/resources/warning.png
BATS/resources/warning_out.png
BATS/resources/font/Bitter-Regular.otf
BATS/resources/font/Caviar_Dreams_Bold.ttf
