Metadata-Version: 1.1
Name: BATS
Version: 1.1.0a1
Summary: https://github.com/ContaTP/BATS-Bayesian-Adaptive-Trial-Simulator
Home-page: https://github.com/ContaTP/BATS-Bayesian-Adaptive-Trial-Simulator
Author: Zhenning Yu
Author-email: yuzhenning.bio@gmail.com
License: GPLv3
Keywords: Bayesian,clinical trial,adaptive trial
Platform: UNKNOWN
Classifier: Development Status :: 5 - Production/Stable
Classifier: Intended Audience :: Science/Research
Classifier: Intended Audience :: Healthcare Industry
Classifier: Topic :: Scientific/Engineering
Classifier: Topic :: Scientific/Engineering :: Medical Science Apps.
Classifier: License :: OSI Approved :: GNU General Public License v3 (GPLv3)
Classifier: Programming Language :: Python :: 3
Classifier: Programming Language :: Python :: 3.3
Classifier: Programming Language :: Python :: 3.4
Classifier: Programming Language :: Python :: 3.5
Classifier: Programming Language :: Cython
Classifier: Natural Language :: English
Classifier: Operating System :: MacOS
Classifier: Operating System :: Microsoft :: Windows
Classifier: Operating System :: POSIX :: Linux
